django_inbox/__init__.py
django_inbox/settings.py
django_inbox/urls.py
django_inbox/wsgi.py
inbox/__init__.py
inbox/admin.py
inbox/apps.py
inbox/forms.py
inbox/models.py
inbox/urls.py
inbox/views.py
inbox/migrations/0001_initial.py
inbox/migrations/__init__.py
inbox/templatetags/__init__.py
inbox/templatetags/inbox_tags.py
inbox/tests/__init__.py
inbox/tests/test_forms.py
inbox/tests/test_models.py
inbox/tests/test_views.py
django_inbox-0.1.dist-info/LICENSE
django_inbox-0.1.dist-info/METADATA
django_inbox-0.1.dist-info/WHEEL
django_inbox-0.1.dist-info/top_level.txt
django_inbox-0.1.dist-info/RECORD
