Metadata-Version: 2.1
Name: django-inbox
Version: 0.1
Summary: ['A not live messaging system that simulates an email inbox']
Home-page: https://gitlab.com/polrodoreda/django-inbox
Author: Pol Rodoreda Valeri
Author-email: pol_rodoreda@hotmail.com
License: MIT
Platform: UNKNOWN
Requires-Dist: Django (>=2.0)
